Metadata-Version: 2.1
Name: SDOFsimulations
Version: 0.0.0.1
Summary: analysis for SDOF oscilator simulations
Home-page: https://www.illarisoft.com/
Author: Edwin Pareja
Author-email: edwinsaulpm@gmail.com
License: UNKNOWN
Platform: UNKNOWN
